{
	"class" : {
		"allPackageNames" : "fn 6/22/2016 00:44",
		"classesFrom:" : "fn 6/22/2016 00:32",
		"classesInPackage:" : "fn 6/22/2016 09:16",
		"codeCoverageClass" : "fn 10/8/2016 14:57",
		"fileExists:" : "fn 4/14/2016 00:56",
		"forceNewFileNamed:" : "fn 10/4/2016 18:02",
		"getAuthor" : "fn 6/13/2016 13:49",
		"getEnv:" : "fn 10/9/2016 21:32",
		"hash:length:" : "fn 10/11/2016 23:03",
		"imagePath" : "fn 9/27/2016 20:13",
		"isHeadless" : "fn 1/27/2016 17:04",
		"isPlatformCompatible" : "fn 1/31/2016 17:57",
		"methodDictOf:" : "fn 10/4/2016 17:25",
		"pathNameDelimiter" : "fn 6/25/2016 00:21",
		"platformSymbol" : "EstebanLorenzano 1/26/2016 17:36",
		"quitImage" : "fn 10/11/2016 18:43",
		"saveImage" : "fn 10/4/2016 16:34",
		"stdout" : "fn 9/27/2016 20:38",
		"stringFor:maxDecimalPlaces:" : "fn 9/28/2016 11:48",
		"testRunnerClass" : "fn 10/4/2016 17:21" },
	"instance" : {
		"load" : "fn 6/13/2016 13:29",
		"readSTONSpec:" : "fn 10/8/2016 15:26",
		"reportImage" : "fn 9/27/2016 20:39" } }
